tests/__init__.py
tests/test_color_conv.py
tests/test_tf.py
tests/test_torch.py
torchstain/__init__.py
torchstain/base/__init__.py
torchstain/base/augmentors/__init__.py
torchstain/base/augmentors/he_augmentor.py
torchstain/base/augmentors/macenko.py
torchstain/base/normalizers/__init__.py
torchstain/base/normalizers/he_normalizer.py
torchstain/base/normalizers/macenko.py
torchstain/base/normalizers/multitarget.py
torchstain/base/normalizers/reinhard.py
torchstain/numpy/__init__.py
torchstain/numpy/augmentors/__init__.py
torchstain/numpy/augmentors/macenko.py
torchstain/numpy/normalizers/__init__.py
torchstain/numpy/normalizers/macenko.py
torchstain/numpy/normalizers/reinhard.py
torchstain/numpy/utils/__init__.py
torchstain/numpy/utils/lab2rgb.py
torchstain/numpy/utils/rgb2lab.py
torchstain/numpy/utils/split.py
torchstain/numpy/utils/stats.py
torchstain/tf/__init__.py
torchstain/tf/augmentors/__init__.py
torchstain/tf/augmentors/macenko.py
torchstain/tf/normalizers/__init__.py
torchstain/tf/normalizers/macenko.py
torchstain/tf/normalizers/reinhard.py
torchstain/tf/utils/__init__.py
torchstain/tf/utils/cov.py
torchstain/tf/utils/lab2rgb.py
torchstain/tf/utils/percentile.py
torchstain/tf/utils/rgb2lab.py
torchstain/tf/utils/solveLS.py
torchstain/tf/utils/split.py
torchstain/tf/utils/stats.py
torchstain/torch/__init__.py
torchstain/torch/augmentors/__init__.py
torchstain/torch/augmentors/macenko.py
torchstain/torch/normalizers/__init__.py
torchstain/torch/normalizers/macenko.py
torchstain/torch/normalizers/multitarget.py
torchstain/torch/normalizers/reinhard.py
torchstain/torch/utils/__init__.py
torchstain/torch/utils/cov.py
torchstain/torch/utils/lab2rgb.py
torchstain/torch/utils/percentile.py
torchstain/torch/utils/rgb2lab.py
torchstain/torch/utils/split.py
torchstain/torch/utils/stats.py
torchstain-1.4.0.dist-info/LICENSE
torchstain-1.4.0.dist-info/METADATA
torchstain-1.4.0.dist-info/WHEEL
torchstain-1.4.0.dist-info/top_level.txt
torchstain-1.4.0.dist-info/RECORD
