Metadata-Version: 2.2
Name: torchstain
Version: 1.4.0
Summary: Stain normalization tools for histological analysis and computational pathology
Home-page: https://github.com/EIDOSlab/torchstain
Author: Carlo Alberto Barbano, André Pedersen
Author-email: eidoslab@di.unito.it
License: MIT
Classifier: Development Status :: 4 - Beta
Classifier: Intended Audience :: Developers
Classifier: Topic :: Scientific/Engineering :: Artificial Intelligence
Classifier: Programming Language :: Python :: 3.6
Classifier: Programming Language :: Python :: 3.7
Classifier: Programming Language :: Python :: 3.8
Classifier: Programming Language :: Python :: 3.9
Classifier: License :: OSI Approved :: MIT License
Classifier: Operating System :: OS Independent
Requires-Python: >=3.6
License-File: LICENSE
Requires-Dist: numpy
Provides-Extra: tf
Requires-Dist: tensorflow; extra == "tf"
Provides-Extra: torch
Requires-Dist: torch; extra == "torch"
Dynamic: author
Dynamic: author-email
Dynamic: classifier
Dynamic: description
Dynamic: description-content-type
Dynamic: home-page
Dynamic: license
Dynamic: provides-extra
Dynamic: requires-dist
Dynamic: requires-python
Dynamic: summary
